cardiff-b0/simWorkspace/booth4_v2/rtl/booth4_v2.v
// Generator : SpinalHDL v1.4.2    git head : 804c7bd7b7feaddcc1d25ecef6c208fd5f776f79
// Component : booth4_v2
// Git hash  : ed79254912e4e0116b93338ee750ed4f28bc3df0



module booth4_v2 (
  input               io_din_vld,
  input      [7:0]    io_dinA,
  input      [7:0]    io_dinB,
  output              io_dout_vld,
  output     [15:0]   io_dout,
  input               clk,
  input               reset
);
  reg        [17:0]   shiftReg;
  wire       [2:0]    flag_bits;
  wire       [8:0]    NegativeB;
  wire       [8:0]    Negative2B;
  wire       [8:0]    PositiveB;
  wire       [8:0]    Positive2B;
  wire       [8:0]    AddB;
  wire       [8:0]    Add2B;
  wire       [8:0]    MinusB;
  wire       [8:0]    Minus2B;
  reg        [1:0]    cal_cnt;
  reg                 cal_en;
  wire       [8:0]    shiftReg_low;
  wire       [8:0]    shiftReg_high;
  reg        [8:0]    beforeshift;
  wire       [17:0]   aftershift;
  reg                 cal_en_regNext;

  assign flag_bits = shiftReg[2 : 0];
  assign NegativeB = (- PositiveB);
  assign PositiveB = {{1{io_dinB[7]}}, io_dinB};
  assign Negative2B = (NegativeB <<< 1);
  assign Positive2B = (PositiveB <<< 1);
  assign shiftReg_low = shiftReg[8 : 0];
  assign shiftReg_high = shiftReg[17 : 9];
  assign AddB = ($signed(shiftReg_high) + $signed(PositiveB));
  assign Add2B = ($signed(shiftReg_high) + $signed(Positive2B));
  assign MinusB = ($signed(shiftReg_high) + $signed(NegativeB));
  assign Minus2B = ($signed(shiftReg_high) + $signed(Negative2B));
  always @ (*) begin
    case(flag_bits)
      3'b000, 3'b111 : begin
        beforeshift = shiftReg_high;
      end
      3'b001, 3'b010 : begin
        beforeshift = AddB;
      end
      3'b101, 3'b110 : begin
        beforeshift = MinusB;
      end
      3'b011 : begin
        beforeshift = Add2B;
      end
      default : begin
        beforeshift = Minus2B;
      end
    endcase
  end

  assign aftershift = ({beforeshift,shiftReg_low} >>> 2);
  assign io_dout_vld = ((! cal_en) && cal_en_regNext);
  assign io_dout = shiftReg[16 : 1];
  always @ (posedge clk or posedge reset) begin
    if (reset) begin
      shiftReg <= 18'h0;
      cal_cnt <= 2'b00;
      cal_en <= 1'b0;
    end else begin
      if(io_din_vld)begin
        cal_en <= 1'b1;
      end else begin
        if((cal_cnt == 2'b11))begin
          cal_en <= 1'b0;
        end
      end
      if(cal_en)begin
        cal_cnt <= (cal_cnt + 2'b01);
      end else begin
        if(io_din_vld)begin
          cal_cnt <= 2'b00;
        end
      end
      if(io_din_vld)begin
        shiftReg <= {{9'h0,io_dinA},1'b0};
      end else begin
        if(cal_en)begin
          shiftReg <= aftershift;
        end
      end
    end
  end

  always @ (posedge clk) begin
    cal_en_regNext <= cal_en;
  end


endmodule

cardiff-b0/simWorkspace/booth4_v2/test.vcd
$version Generated by VerilatedVcd $end
$date Wed Dec 22 18:24:40 2021
 $end
$timescale   1ps $end

 $scope module TOP $end
  $var wire  1 4 clk $end
  $var wire  8 0 io_dinA [7:0] $end
  $var wire  8 1 io_dinB [7:0] $end
  $var wire  1 / io_din_vld $end
  $var wire 16 3 io_dout [15:0] $end
  $var wire  1 2 io_dout_vld $end
  $var wire  1 5 reset $end
  $scope module booth4_v2 $end
   $var wire  9 6 Add2B [8:0] $end
   $var wire  9 ' AddB [8:0] $end
   $var wire  9 7 Minus2B [8:0] $end
   $var wire  9 ( MinusB [8:0] $end
   $var wire  9 $ Negative2B [8:0] $end
   $var wire  9 # NegativeB [8:0] $end
   $var wire  9 & Positive2B [8:0] $end
   $var wire  9 % PositiveB [8:0] $end
   $var wire 18 9 aftershift [17:0] $end
   $var wire  9 8 beforeshift [8:0] $end
   $var wire  2 + cal_cnt [1:0] $end
   $var wire  1 , cal_en $end
   $var wire  1 : cal_en_regNext $end
   $var wire  1 4 clk $end
   $var wire  3 * flag_bits [2:0] $end
   $var wire  8 0 io_dinA [7:0] $end
   $var wire  8 1 io_dinB [7:0] $end
   $var wire  1 / io_din_vld $end
   $var wire 16 3 io_dout [15:0] $end
   $var wire  1 2 io_dout_vld $end
   $var wire  1 5 reset $end
   $var wire 18 ) shiftReg [17:0] $end
   $var wire  9 . shiftReg_high [8:0] $end
   $var wire  9 - shiftReg_low [8:0] $end
  $upscope $end
 $upscope $end
$enddefinitions $end


#0
b000000100 #
b000001000 $
b111111100 %
b111111000 &
b111111100 '
b000000100 (
b000000000000000000 )
b000 *
b00 +
0,
b000000000 -
b000000000 .
0/
b00011110 0
b11111100 1
12
b0000000000000000 3
04
15
b111111000 6
b000001000 7
b000000000 8
b000000000000000000 9
1:
#80
05
#85
02
14
0:
#87
04
#89
14
#91
04
#93
14
#95
04
#97
14
#99
04
#100
#101
b110100101 #
b101001010 $
b001011011 %
b010110110 &
b001011011 '
b110100101 (
1/
b00110111 0
b01011011 1
14
b010110110 6
b101001010 7
#103
04
#105
b000000000001101110 )
b110 *
1,
b001101110 -
0/
b0000000000110111 3
14
b110100101 8
b111101001010011011 9
#107
04
#109
b001000100 '
b110001110 (
b111101001010011011 )
b011 *
b01 +
b010011011 -
b111101001 .
b1110100101001101 3
14
b010011111 6
b100110011 7
b010011111 8
b000100111110100110 9
1:
#111
04
#113
b010000010 '
b111001100 (
b000100111110100110 )
b110 *
b10 +
b110100110 -
b000100111 .
b0010011111010011 3
14
b011011101 6
b101110001 7
b111001100 8
b111110011001101001 9
#115
04
#117
b001001110 '
b110011000 (
b111110011001101001 )
b001 *
b11 +
b001101001 -
b111110011 .
b1111001100110100 3
14
b010101001 6
b100111101 7
b001001110 8
b000010011100011010 9
#119
04
#121
b001101110 '
b110111000 (
b000010011100011010 )
b010 *
b00 +
0,
b100011010 -
b000010011 .
12
b0001001110001101 3
14
b011001001 6
b101011101 7
b001101110 8
b000011011101000110 9
#123
04
#125
02
14
0:
